cd_randomizer/__version__.py
cd_randomizer/rand.py
cd_randomizer/examples/example_usage.py
cd_randomizer/tests/test_rand.py
cd_randomizer-0.0.2.dist-info/LICENSE.md
cd_randomizer-0.0.2.dist-info/LICENSE.txt
cd_randomizer-0.0.2.dist-info/METADATA
cd_randomizer-0.0.2.dist-info/WHEEL
cd_randomizer-0.0.2.dist-info/top_level.txt
cd_randomizer-0.0.2.dist-info/RECORD
