Metadata-Version: 2.1
Name: cd_randomizer
Version: 0.0.2
Summary: A simple CD randomizer package.
Author-email: Nicholas Capasso <codedocta@gmail.com>
License: MIT License
Project-URL: Home, https://github.com/codedocta/cd_randomizer
Classifier: Programming Language :: Python :: 3
Classifier: License :: OSI Approved :: MIT License
Classifier: Operating System :: OS Independent
Requires-Python: >=3.6
License-File: LICENSE.md
License-File: LICENSE.txt
